LICENSE.md
MANIFEST.in
README.md
setup.py
admin_adminlte/__init__.py
admin_adminlte/admin.py
admin_adminlte/apps.py
admin_adminlte/forms.py
admin_adminlte/models.py
admin_adminlte/tests.py
admin_adminlte/urls.py
admin_adminlte/utils.py
admin_adminlte/views.py
admin_adminlte/migrations/__init__.py
admin_adminlte/static/dist/css/adminlte.css
admin_adminlte/static/dist/css/adminlte.css.map
admin_adminlte/static/dist/css/adminlte.min.css
admin_adminlte/static/dist/css/adminlte.min.css.map
admin_adminlte/static/dist/css/forms.css
admin_adminlte/static/dist/css/widgets.css
admin_adminlte/static/dist/css/alt/adminlte.components.css
admin_adminlte/static/dist/css/alt/adminlte.components.css.map
admin_adminlte/static/dist/css/alt/adminlte.components.min.css
admin_adminlte/static/dist/css/alt/adminlte.components.min.css.map
admin_adminlte/static/dist/css/alt/adminlte.core.css
admin_adminlte/static/dist/css/alt/adminlte.core.css.map
admin_adminlte/static/dist/css/alt/adminlte.core.min.css
admin_adminlte/static/dist/css/alt/adminlte.core.min.css.map
admin_adminlte/static/dist/css/alt/adminlte.extra-components.css
admin_adminlte/static/dist/css/alt/adminlte.extra-components.css.map
admin_adminlte/static/dist/css/alt/adminlte.extra-components.min.css
admin_adminlte/static/dist/css/alt/adminlte.extra-components.min.css.map
admin_adminlte/static/dist/css/alt/adminlte.light.css
admin_adminlte/static/dist/css/alt/adminlte.light.css.map
admin_adminlte/static/dist/css/alt/adminlte.light.min.css
admin_adminlte/static/dist/css/alt/adminlte.light.min.css.map
admin_adminlte/static/dist/css/alt/adminlte.pages.css
admin_adminlte/static/dist/css/alt/adminlte.pages.css.map
admin_adminlte/static/dist/css/alt/adminlte.pages.min.css
admin_adminlte/static/dist/css/alt/adminlte.pages.min.css.map
admin_adminlte/static/dist/css/alt/adminlte.plugins.css
admin_adminlte/static/dist/css/alt/adminlte.plugins.css.map
admin_adminlte/static/dist/css/alt/adminlte.plugins.min.css
django_admin_adminlte.egg-info/PKG-INFO
django_admin_adminlte.egg-info/SOURCES.txt
django_admin_adminlte.egg-info/dependency_links.txt
django_admin_adminlte.egg-info/not-zip-safe
django_admin_adminlte.egg-info/top_level.txt
